DeepLogger/DeepLogger.py
DeepLogger/__init__.py
DeepLogger-0.0.5.dist-info/LICENSE
DeepLogger-0.0.5.dist-info/METADATA
DeepLogger-0.0.5.dist-info/WHEEL
DeepLogger-0.0.5.dist-info/top_level.txt
DeepLogger-0.0.5.dist-info/RECORD
