Metadata-Version: 2.1
Name: DeepLogger
Version: 0.0.5
Summary: Easily configure, simple granular loggers for all your modules.
Home-page: https://github.com/aastopher/DeepLogger
Author: Aaron Stopher
License: UNKNOWN
Project-URL: Bug Tracker, https://github.com/aastopher/DeepLogger/issues
Keywords: python,logger,CLI,deep logging,deep logger,deep
Platform: UNKNOWN
Classifier: Programming Language :: Python :: 3
Classifier: License :: OSI Approved :: MIT License
Classifier: Operating System :: OS Independent
Requires-Python: >=3.6
License-File: LICENSE
